biocypher/__init__.py
biocypher/_core.py
biocypher/_create.py
biocypher/_deduplicate.py
biocypher/_get.py
biocypher/_graph.py
biocypher/_logger.py
biocypher/_mapping.py
biocypher/_metadata.py
biocypher/_misc.py
biocypher/_ontology.py
biocypher/_translate.py
biocypher/_workflow.py
biocypher/_config/__init__.py
biocypher/_config/biocypher_config.yaml
biocypher/_config/test_config.yaml
biocypher/_config/test_schema_config.yaml
biocypher/_config/test_schema_config_disconnected.yaml
biocypher/_config/test_schema_config_extended.yaml
biocypher/output/__init__.py
biocypher/output/connect/__init__.py
biocypher/output/connect/_get_connector.py
biocypher/output/connect/_neo4j_driver.py
biocypher/output/connect/_neo4j_driver_wrapper.py
biocypher/output/in_memory/__init__.py
biocypher/output/in_memory/_airr.py
biocypher/output/in_memory/_get_in_memory_kg.py
biocypher/output/in_memory/_in_memory_kg.py
biocypher/output/in_memory/_networkx.py
biocypher/output/in_memory/_pandas.py
biocypher/output/templates/powershell_template.ps1
biocypher/output/write/__init__.py
biocypher/output/write/_batch_writer.py
biocypher/output/write/_get_writer.py
biocypher/output/write/_writer.py
biocypher/output/write/graph/__init__.py
biocypher/output/write/graph/_airr.py
biocypher/output/write/graph/_arangodb.py
biocypher/output/write/graph/_neo4j.py
biocypher/output/write/graph/_networkx.py
biocypher/output/write/graph/_owl.py
biocypher/output/write/graph/_rdf.py
biocypher/output/write/relational/__init__.py
biocypher/output/write/relational/_csv.py
biocypher/output/write/relational/_postgresql.py
biocypher/output/write/relational/_sqlite.py
biocypher-0.12.5.dist-info/METADATA
biocypher-0.12.5.dist-info/WHEEL
biocypher-0.12.5.dist-info/licenses/LICENSE
biocypher-0.12.5.dist-info/licenses/NOTICE
biocypher-0.12.5.dist-info/RECORD
