Metadata-Version: 2.4
Name: biocypher
Version: 0.12.5
Summary: A unifying framework for biomedical research knowledge graphs
Project-URL: Homepage, https://biocypher.org
Project-URL: Documentation, https://biocypher.org
Project-URL: Repository, https://github.com/biocypher/biocypher
Project-URL: Issues, https://github.com/biocypher/biocypher/issues
Project-URL: Bug Tracker, https://github.com/biocypher/biocypher/issues
Author-email: Sebastian Lobentanzer <sebastian.lobentanzer@gmail.com>, Denes Turei <turei.denes@gmail.com>
License: Apache-2.0
License-File: LICENSE
License-File: NOTICE
Keywords: bioinformatics,biomedical-data,graph-database,knowledge-graph
Classifier: Development Status :: 3 - Alpha
Classifier: Intended Audience :: Developers
Classifier: Intended Audience :: Science/Research
Classifier: License :: OSI Approved :: Apache Software License
Classifier: Natural Language :: English
Classifier: Operating System :: OS Independent
Classifier: Programming Language :: Python
Classifier: Topic :: Scientific/Engineering :: Bio-Informatics
Requires-Python: >=3.10
Requires-Dist: appdirs
Requires-Dist: more-itertools
Requires-Dist: networkx>=3.0
Requires-Dist: pandas>=2.0.1
Requires-Dist: pooch>=1.7.0
Requires-Dist: pyyaml>=5.0
Requires-Dist: rdflib>=6.2.0
Requires-Dist: toml>=0.10.2
Requires-Dist: tqdm>=4.65.0
Requires-Dist: treelib==1.6.4
Provides-Extra: neo4j
Requires-Dist: neo4j>=5.0; extra == 'neo4j'
Provides-Extra: scirpy
Requires-Dist: scirpy>=0.22.0; extra == 'scirpy'
